papercut/__init__.py
papercut/api.py
papercut/papercut.py
papercut-0.1.1.dist-info/DESCRIPTION.rst
papercut-0.1.1.dist-info/METADATA
papercut-0.1.1.dist-info/RECORD
papercut-0.1.1.dist-info/WHEEL
papercut-0.1.1.dist-info/metadata.json
papercut-0.1.1.dist-info/top_level.txt
