Metadata-Version: 2.0
Name: papercut
Version: 0.1.1
Summary: Papercut API
Home-page: https://github.com/kulinacs/papercut
Author: Nicklaus McClendon
Author-email: nicklaus@kulinacs.com
License: ISC
Keywords: papercut printing
Platform: UNKNOWN
Classifier: Development Status :: 3 - Alpha
Classifier: License :: OSI Approved :: ISC License (ISCL)
Classifier: Programming Language :: Python :: 2.7
